il2cpp_strings/__init__.py
il2cpp_strings/patcher.py
il2cpp_strings_patcher-0.1.0.dist-info/licenses/LICENSE
il2cpp_strings_patcher-0.1.0.dist-info/METADATA
il2cpp_strings_patcher-0.1.0.dist-info/WHEEL
il2cpp_strings_patcher-0.1.0.dist-info/top_level.txt
il2cpp_strings_patcher-0.1.0.dist-info/RECORD
