Metadata-Version: 2.4
Name: il2cpp-strings-patcher
Version: 0.1.0
Summary: Utilities to automate the modification to il2cpp string literals in metadata
Author-email: Rosemoe <rosemoe168@gmail.com>
License-Expression: Apache-2.0
Project-URL: Homepage, https://github.com/Rosemoe/il2cpp-strings-patcher
Classifier: Development Status :: 4 - Beta
Classifier: Operating System :: MacOS :: MacOS X
Classifier: Operating System :: Microsoft :: Windows
Classifier: Operating System :: POSIX
Classifier: Topic :: Software Development
Classifier: Topic :: Utilities
Classifier: Intended Audience :: Developers
Classifier: Programming Language :: Python :: 3
Requires-Python: >=3.8
License-File: LICENSE
Dynamic: license-file
